freerouter/__init__.py
freerouter/__version__.py
freerouter/cli/__init__.py
freerouter/cli/config.py
freerouter/cli/main.py
freerouter/cli/request_log_parser.py
freerouter/core/__init__.py
freerouter/core/factory.py
freerouter/core/fetcher.py
freerouter/providers/__init__.py
freerouter/providers/base.py
freerouter/providers/iflow.py
freerouter/providers/modelscope.py
freerouter/providers/oai.py
freerouter/providers/ollama.py
freerouter/providers/openrouter.py
freerouter/providers/static.py
freerouter-0.1.5.dist-info/licenses/LICENSE
freerouter-0.1.5.dist-info/METADATA
freerouter-0.1.5.dist-info/WHEEL
freerouter-0.1.5.dist-info/entry_points.txt
freerouter-0.1.5.dist-info/top_level.txt
freerouter-0.1.5.dist-info/RECORD
